fir_filter.v
`timescale 1ns / 1ps

module fir_filter #(
    parameter N = 4  // Number of taps
)(
    input clk,
    input rst,
    input signed [7:0] x_in,
    output reg signed [15:0] y_out
);

    // Filter coefficients (can be customized)
    // Example: Low-pass filter coefficients
    reg signed [7:0] h [0:N-1];
    initial begin
        h[0] = 8'd1;
        h[1] = 8'd2;
        h[2] = 8'd2;
        h[3] = 8'd1;
    end

    // Shift register for inputs
    reg signed [7:0] x [0:N-1];

    integer i;
    always @(posedge clk or posedge rst) begin
        if (rst) begin
            y_out <= 0;
            for (i = 0; i < N; i = i + 1)
                x[i] <= 0;
        end else begin
            // Shift input samples
            for (i = N-1; i > 0; i = i - 1)
                x[i] <= x[i-1];
            x[0] <= x_in;

            // Compute output
            y_out <= 0;
            for (i = 0; i < N; i = i + 1)
                y_out <= y_out + x[i] * h[i];
        end
    end

endmodule

fir_filter_tb.v
`timescale 1ns / 1ps

module fir_filter_tb;

    reg clk, rst;
    reg signed [7:0] x_in;
    wire signed [15:0] y_out;

    fir_filter uut (
        .clk(clk),
        .rst(rst),
        .x_in(x_in),
        .y_out(y_out)
    );

    initial begin
        $dumpfile("fir_filter.vcd");
        $dumpvars(0, fir_filter_tb);

        clk = 0; rst = 1;
        x_in = 0;
        #10 rst = 0;

        // Apply test input sequence (e.g., impulse + step)
        #10 x_in = 8'd10;
        #10 x_in = 8'd0;
        #10 x_in = 8'd0;
        #10 x_in = 8'd0;
        #10 x_in = 8'd0;
        #10 x_in = 8'd10;
        #10 x_in = 8'd10;
        #10 x_in = 8'd10;
        #10 x_in = 8'd10;
        #50 $finish;
    end

    always #5 clk = ~clk;

endmodule

fir_filter.vcd
$date
	Mon Jul 28 17:36:10 2025
$end
$version
	Icarus Verilog
$end
$timescale
	1ps
$end
$scope module fir_filter_tb $end
$var wire 16 ! y_out [15:0] $end
$var reg 1 " clk $end
$var reg 1 # rst $end
$var reg 8 $ x_in [7:0] $end
$scope module uut $end
$var wire 1 % clk $end
$var wire 1 & rst $end
$var wire 8 ' x_in [7:0] $end
$var integer 32 ( i [31:0] $end
$var reg 16 ) y_out [15:0] $end
$upscope $end
$upscope $end
$enddefinitions $end
#0
$dumpvars
b0 )
b100 (
b0 '
1&
0%
b0 $
1#
0"
b0 !
$end
#5000
b100 (
1"
1%
#10000
0"
0%
0#
0&
#15000
b100 (
1"
1%
#20000
0"
0%
b1010 $
b1010 '
#25000
b100 (
1"
1%
#30000
0"
0%
b0 $
b0 '
#35000
b0 )
b0 !
b100 (
1"
1%
#40000
0"
0%
#45000
b0 )
b0 !
b100 (
1"
1%
#50000
0"
0%
#55000
b0 )
b0 !
b100 (
1"
1%
#60000
0"
0%
#65000
b1010 )
b1010 !
b100 (
1"
1%
#70000
0"
0%
b1010 $
b1010 '
#75000
b1010 )
b1010 !
b100 (
1"
1%
#80000
0"
0%
#85000
b1010 )
b1010 !
b100 (
1"
1%
#90000
0"
0%
#95000
b1010 )
b1010 !
b100 (
1"
1%
#100000
0"
0%
#105000
b1010 )
b1010 !
b100 (
1"
1%
#110000
0"
0%
#115000
b10100 )
b10100 !
b100 (
1"
1%
#120000
0"
0%
#125000
b11110 )
b11110 !
b100 (
1"
1%
#130000
0"
0%
#135000
b101000 )
b101000 !
b100 (
1"
1%
#140000
0"
0%
#145000
b110010 )
b110010 !
b100 (
1"
1%
